{
    "EYC_DRAUGHTS_2017": "МЧЕ 2017 по шашкам-100",
    "RESULTS": "Результаты",
    "REGULATIONS": "Регламент",

    "PLAYER":"Игрок",
    "RATING":"Рейтинг",
    "TITLE":"Звание",
    "COUNTRY":"Страна",

    "19th_European_Youth_Championship": "19-ый Молодежный Чемпионат Европы",
    "Welcome_to_the_European_Youth_Championship": "Добро пожаловать на Молодежный Чемпионат Европы!",
    "There_will_be_more_information_soon_on_this_site":  "В скором времени на сайте появится больше информации.",

    "Tournament_details": "Подробности турнира",
    "Place": "Место проведения",
    "Players_number": "Количество игроков",
    "Current_Round": "Текущий тур",
    "Arbiter": "Судья",   
    "Days": "Дни проведения"                  
}